agntcy/identity/core/v1alpha1/errors_pb2.py
agntcy/identity/core/v1alpha1/errors_pb2_grpc.py
agntcy/identity/core/v1alpha1/id_pb2.py
agntcy/identity/core/v1alpha1/id_pb2_grpc.py
agntcy/identity/core/v1alpha1/issuer_pb2.py
agntcy/identity/core/v1alpha1/issuer_pb2_grpc.py
agntcy/identity/core/v1alpha1/jwk_pb2.py
agntcy/identity/core/v1alpha1/jwk_pb2_grpc.py
agntcy/identity/core/v1alpha1/mcp_pb2.py
agntcy/identity/core/v1alpha1/mcp_pb2_grpc.py
agntcy/identity/core/v1alpha1/vc_pb2.py
agntcy/identity/core/v1alpha1/vc_pb2_grpc.py
agntcy/identity/node/v1alpha1/id_service_pb2.py
agntcy/identity/node/v1alpha1/id_service_pb2_grpc.py
agntcy/identity/node/v1alpha1/issuer_service_pb2.py
agntcy/identity/node/v1alpha1/issuer_service_pb2_grpc.py
agntcy/identity/node/v1alpha1/openapi_pb2.py
agntcy/identity/node/v1alpha1/openapi_pb2_grpc.py
agntcy/identity/node/v1alpha1/vc_service_pb2.py
agntcy/identity/node/v1alpha1/vc_service_pb2_grpc.py
agntcyidentity/__init__.py
agntcyidentity/client.py
agntcyidentity/constant.py
agntcyidentity/log.py
agntcyidentity/sdk.py
google/api/annotations_pb2.py
google/api/annotations_pb2_grpc.py
google/api/http_pb2.py
google/api/http_pb2_grpc.py
openapiv3/OpenAPIv3_pb2.py
openapiv3/OpenAPIv3_pb2_grpc.py
openapiv3/annotations_pb2.py
openapiv3/annotations_pb2_grpc.py
agntcy_identity_sdk-0.0.18.dist-info/METADATA
agntcy_identity_sdk-0.0.18.dist-info/WHEEL
agntcy_identity_sdk-0.0.18.dist-info/top_level.txt
agntcy_identity_sdk-0.0.18.dist-info/RECORD
