Metadata-Version: 2.4
Name: agntcy-identity-sdk
Version: 0.0.18
Summary: Identity SDK for Python
Author-email: Jean Diaconu <jdiaconu@cisco.com>, Corentin Passeron <cpassero@cisco.com>
License-Expression: Apache-2.0
Project-URL: Homepage, https://github.com/agntcy/identity
Project-URL: Bug Tracker, https://github.com/agntcy/identity/issues
Classifier: Programming Language :: Python :: 3
Requires-Python: >=3.8
Requires-Dist: grpcio
Requires-Dist: protobuf
Requires-Dist: grpcio-tools
Requires-Dist: protoc_gen_openapiv2
Requires-Dist: pyjwt
Requires-Dist: python-dotenv
